jsonlink.py
jsonlink-0.0.9.dist-info/LICENSE
jsonlink-0.0.9.dist-info/METADATA
jsonlink-0.0.9.dist-info/WHEEL
jsonlink-0.0.9.dist-info/top_level.txt
jsonlink-0.0.9.dist-info/RECORD
