Metadata-Version: 2.1
Name: jsonlink
Version: 0.0.9
Summary: Allows for a python object to be updated via a dictionary or JSON file.
Home-page: UNKNOWN
Author: UNKNOWN
Author-email: UNKNOWN
License: UNKNOWN
Platform: UNKNOWN
